README.rst
setup.py
auth/__init__.py
auth/admin.py
auth/filters.py
auth/forms.py
auth/models.py
auth/resources.py
auth/migrations/0001_initial.py
auth/migrations/0002_auto__add_unique_customuser_mobile.py
auth/migrations/0003_auto__add_field_customuser_unique_token__add_field_customuser_unique_t.py
auth/migrations/0004_auto__chg_field_customuser_unique_token__add_field_learner_last_maths_.py
auth/migrations/0005_auto__add_field_learner_last_active_date.py
auth/migrations/__init__.py
communication/__init__.py
communication/admin.py
communication/models.py
communication/tasks.py
communication/tests.py
communication/utils.py
communication/migrations/0001_initial.py
communication/migrations/0002_auto__add_field_message_author__add_field_message_direction.py
communication/migrations/0003_auto__add_field_discussion_author__add_field_chatmessage_author.py
communication/migrations/0004_auto__chg_field_message_publishdate__chg_field_discussion_publishdate_.py
communication/migrations/0005_auto__add_field_post_big_image__add_field_post_small_image__add_field_.py
communication/migrations/0006_auto__add_messagestatus.py
communication/migrations/0007_auto__del_unique_message_name.py
communication/migrations/0008_auto__add_field_discussion_course__add_field_discussion_module__add_fi.py
communication/migrations/0009_auto__chg_field_discussion_moderated.py
communication/migrations/0010_auto__chg_field_page_name.py
communication/migrations/0011_auto__add_sms.py
communication/migrations/0012_auto__add_field_sms_msisdn.py
communication/migrations/__init__.py
content/__init__.py
content/admin.py
content/models.py
content/tests.py
content/migrations/0001_initial.py
content/migrations/0002_auto__chg_field_learningchapter_name__chg_field_learningchapter_descri.py
content/migrations/0003_auto__add_field_testingquestion_textbook_link.py
content/migrations/0004_test_question_default.py
content/migrations/0005_auto__add_field_testingquestion_module.py
django_mobileu.egg-info/PKG-INFO
django_mobileu.egg-info/SOURCES.txt
django_mobileu.egg-info/dependency_links.txt
django_mobileu.egg-info/requires.txt
django_mobileu.egg-info/top_level.txt
