Metadata-Version: 1.0
Name: django-mobileu
Version: 1.1.0
Summary: The MobileU MVP framework allows other developers to easily build mobile education sites.
Home-page: www.praekelt.co.za
Author: praekelt
Author-email: info@praekelt.co.za
License: UNKNOWN
Platform: UNKNOWN
